hearthstone_data/BUILD
hearthstone_data/BountyDefs.xml
hearthstone_data/CardDefs.xml
hearthstone_data/MercenaryDefs.xml
hearthstone_data/__init__.py
hearthstone_data/Strings/deDE/GAMEPLAY.txt
hearthstone_data/Strings/deDE/GAMEPLAY_AUDIO.txt
hearthstone_data/Strings/deDE/GLOBAL.txt
hearthstone_data/Strings/deDE/GLUE.txt
hearthstone_data/Strings/deDE/MISSION.txt
hearthstone_data/Strings/deDE/MISSION_AUDIO.txt
hearthstone_data/Strings/deDE/PRESENCE.txt
hearthstone_data/Strings/deDE/TUTORIAL.txt
hearthstone_data/Strings/deDE/TUTORIAL_AUDIO.txt
hearthstone_data/Strings/deDE/ZILLIAX_DELUXE_3000.txt
hearthstone_data/Strings/enUS/GAMEPLAY.txt
hearthstone_data/Strings/enUS/GAMEPLAY_AUDIO.txt
hearthstone_data/Strings/enUS/GLOBAL.txt
hearthstone_data/Strings/enUS/GLUE.txt
hearthstone_data/Strings/enUS/MISSION.txt
hearthstone_data/Strings/enUS/MISSION_AUDIO.txt
hearthstone_data/Strings/enUS/PRESENCE.txt
hearthstone_data/Strings/enUS/TUTORIAL.txt
hearthstone_data/Strings/enUS/TUTORIAL_AUDIO.txt
hearthstone_data/Strings/enUS/ZILLIAX_DELUXE_3000.txt
hearthstone_data/Strings/esES/GAMEPLAY.txt
hearthstone_data/Strings/esES/GAMEPLAY_AUDIO.txt
hearthstone_data/Strings/esES/GLOBAL.txt
hearthstone_data/Strings/esES/GLUE.txt
hearthstone_data/Strings/esES/MISSION.txt
hearthstone_data/Strings/esES/MISSION_AUDIO.txt
hearthstone_data/Strings/esES/PRESENCE.txt
hearthstone_data/Strings/esES/TUTORIAL.txt
hearthstone_data/Strings/esES/TUTORIAL_AUDIO.txt
hearthstone_data/Strings/esES/ZILLIAX_DELUXE_3000.txt
hearthstone_data/Strings/esMX/GAMEPLAY.txt
hearthstone_data/Strings/esMX/GAMEPLAY_AUDIO.txt
hearthstone_data/Strings/esMX/GLOBAL.txt
hearthstone_data/Strings/esMX/GLUE.txt
hearthstone_data/Strings/esMX/MISSION.txt
hearthstone_data/Strings/esMX/MISSION_AUDIO.txt
hearthstone_data/Strings/esMX/PRESENCE.txt
hearthstone_data/Strings/esMX/TUTORIAL.txt
hearthstone_data/Strings/esMX/TUTORIAL_AUDIO.txt
hearthstone_data/Strings/esMX/ZILLIAX_DELUXE_3000.txt
hearthstone_data/Strings/frFR/GAMEPLAY.txt
hearthstone_data-233275.1.dist-info/METADATA
hearthstone_data-233275.1.dist-info/WHEEL
hearthstone_data-233275.1.dist-info/top_level.txt
hearthstone_data-233275.1.dist-info/zip-safe
hearthstone_data-233275.1.dist-info/RECORD
